jpe_types/__init__.py
jpe_types/setup.py
jpe_types/caching/__init__.py
jpe_types/caching/cachDirPy.py
jpe_types/conversions/__init__.py
jpe_types/conversions/_temp.py
jpe_types/conversions/dict.py
jpe_types/conversions/intConversions.json
jpe_types/conversions/intager.py
jpe_types/logging/__init__.py
jpe_types/logging/logUtils.py
jpe_types/logging/loggingConfig.json
jpe_types/logging/stepLogging.py
jpe_types/logging/threadLogging.py
jpe_types/paralel/__init__.py
jpe_types/paralel/multiprocessing.py
jpe_types/paralel/thread.py
jpe_types/utils/__init__.py
jpe_types/utils/copy.py
jpe_types/utils/logScanner.py
jpe_types/utils/Optimizations/build.py
jpe_types/utils/Optimizations/subScripts.cpp
jpe_types/utils/Optimizations/subScripts.pyx
jpe_types/utils/Optimizations/jpe_typeUtilsExtentions/FileScanner.h
jpe_types/utils/Optimizations/jpe_typeUtilsExtentions/MainThread.log
jpe_types/utils/Optimizations/jpe_typeUtilsExtentions/jpe_typeUtilsExtentions.cpp
jpe_types/utils/Optimizations/jpe_typeUtilsExtentions/jpe_typeUtilsExtentions.sln
jpe_types/utils/Optimizations/jpe_typeUtilsExtentions/jpe_typeUtilsExtentions.vcxproj
jpe_types/utils/Optimizations/jpe_typeUtilsExtentions/jpe_typeUtilsExtentions.vcxproj.filters
jpe_types/utils/Optimizations/jpe_typeUtilsExtentions/jpe_typeUtilsExtentions.vcxproj.user
jpe_types-0.0.0.5.dist-info/METADATA
jpe_types-0.0.0.5.dist-info/WHEEL
jpe_types-0.0.0.5.dist-info/top_level.txt
jpe_types-0.0.0.5.dist-info/RECORD
