Metadata-Version: 2.1
Name: jpe-types
Version: 0.0.0.5
Summary: slitly improved python types
Home-page: https://github.com/JulianWww/jpe_types
Author: Julian Wandhoven
Author-email: julian.wandhoven@fgz.ch
License: wtfpl
Download-URL: https://github.com/JulianWww/jpe_types/archive/loggingPathc.tar.gz
Keywords: dtypes,jpe,utils,paralel,logging
Platform: UNKNOWN
Classifier: Development Status :: 3 - Alpha
Classifier: Intended Audience :: Developers
Classifier: Topic :: Software Development :: Build Tools
Classifier: License :: OSI Approved :: MIT License
Classifier: Programming Language :: Python :: 3.6
Classifier: Programming Language :: Python :: 3
Requires-Dist: cython
